saapi/__init__.py
saapi/authentication.py
saapi/countries.py
saapi/errors.py
saapi/query_base.py
saapi/saapi.py
saapi/str_enum.py
saapi/mutations/generate_short_link.py
saapi/mutations/mutations.py
saapi/queries/__init__.py
saapi/queries/conversion_report.py
saapi/queries/product_offer_v2.py
saapi/queries/queries.py
saapi/queries/report_query_base.py
saapi/queries/shop_offer_v2.py
saapi/queries/shopee_offer_v2.py
saapi/queries/validated_report.py
saapi-0.2.dist-info/licenses/LICENSE
saapi-0.2.dist-info/METADATA
saapi-0.2.dist-info/WHEEL
saapi-0.2.dist-info/top_level.txt
saapi-0.2.dist-info/RECORD
