Metadata-Version: 2.4
Name: saapi
Version: 0.2
Summary: Simple wrapper for Shopee Affiliate API.
Author-email: Renan Galvão <renan.m.galvao@gmail.com>
License-Expression: MIT
Project-URL: Source, https://github.com/RenanGalvao/saapi
Project-URL: Bug Tracker, https://github.com/RenanGalvao/saapi/issues
Keywords: Shopee,API
Classifier: Development Status :: 4 - Beta
Classifier: Intended Audience :: Developers
Classifier: Operating System :: OS Independent
Classifier: Programming Language :: Python
Classifier: Programming Language :: Python :: 3
Classifier: Programming Language :: Python :: 3.9
Classifier: Programming Language :: Python :: 3.10
Classifier: Programming Language :: Python :: 3.11
Classifier: Programming Language :: Python :: 3.12
Classifier: Programming Language :: Python :: 3.13
Classifier: Topic :: Internet :: WWW/HTTP
Classifier: Topic :: Utilities
Requires-Python: >=3.9
License-File: LICENSE
Requires-Dist: requests
Requires-Dist: typing_extensions
Provides-Extra: tests
Requires-Dist: pytest; extra == "tests"
Requires-Dist: pytest-mock; extra == "tests"
Requires-Dist: pytest-cov; extra == "tests"
Requires-Dist: tox; extra == "tests"
Provides-Extra: all
Requires-Dist: saapi[tests]; extra == "all"
Dynamic: license-file
